AUTHORS.rst
CHANGELOG.rst
CONTRIBUTING.rst
LICENSE
MANIFEST.in
README.rst
setup.cfg
setup.py
docs/Makefile
docs/authors.rst
docs/conf.py
docs/contributing.rst
docs/history.rst
docs/index.rst
docs/installation.rst
docs/make.bat
docs/readme.rst
docs/usage.rst
msspeak/__init__.py
msspeak/command_line.py
msspeak/get_listvoice.py
msspeak/msspeak.py
msspeak/voices.py
python_msspeak.egg-info/PKG-INFO
python_msspeak.egg-info/SOURCES.txt
python_msspeak.egg-info/dependency_links.txt
python_msspeak.egg-info/entry_points.txt
python_msspeak.egg-info/not-zip-safe
python_msspeak.egg-info/requires.txt
python_msspeak.egg-info/top_level.txt
tests/__init__.py
tests/test_msspeak.py