Metadata-Version: 1.1
Name: python-msspeak
Version: 0.6.0
Summary: Text-To-Speech with MSSpeak
Home-page: https://github.com/newfies-dialer/python-msspeak
Author: Areski Belaid
Author-email: areski@gmail.com
License: MIT
Keywords: mstranslator,tts,speech
Platform: UNKNOWN
Classifier: Development Status :: 2 - Pre-Alpha
Classifier: Intended Audience :: Developers
Classifier: License :: OSI Approved :: MIT License
Classifier: Natural Language :: English
Classifier: Programming Language :: Python :: 2
Classifier: Programming Language :: Python :: 2.7
Classifier: Programming Language :: Python :: 3
Classifier: Programming Language :: Python :: 3.3
Classifier: Programming Language :: Python :: 3.4
Classifier: Programming Language :: Python :: 3.5
Classifier: Programming Language :: Python :: 3.6
